[
  {
    "id": 1,
    "Модель": "ААВ",
    "Цена": 500,
    "category": "Очки",
    "image_url": "https://raw.githubusercontent.com/aflemo/Goods/refs/heads/main/AAB-ochi.jpg"
  },
  {
    "id": 2,
    "Модель": "АА",
    "Цена": 450,
    "category": "Очки",
    "image_url": "https://raw.githubusercontent.com/aflemo/Goods/refs/heads/main/AA-ochi.jpg"
  },
  {
    "id": 3,
    "Модель": "SS24",
    "Цена": 1800,
    "category": "Очки",
    "image_url": "https://raw.githubusercontent.com/aflemo/Goods/refs/heads/main/SS24-ochi.jpg"
  }
]
